pytest_my_cool_lib/__init__.py
pytest_my_cool_lib/export_result_plugin.py
pytest_my_cool_lib/hello_world_plugin.py
pytest_my_cool_lib/logger_plugin.py
pytest_my_cool_lib-0.1.3.dist-info/METADATA
pytest_my_cool_lib-0.1.3.dist-info/WHEEL
pytest_my_cool_lib-0.1.3.dist-info/entry_points.txt
pytest_my_cool_lib-0.1.3.dist-info/RECORD
