Metadata-Version: 2.1
Name: pytest-my-cool-lib
Version: 0.1.3
Summary: 
Author: maksym.biriukov
Author-email: maksym.biriukov@eleks.com
Requires-Python: >=3.8,<4.0
Classifier: Programming Language :: Python :: 3
Classifier: Programming Language :: Python :: 3.8
Classifier: Programming Language :: Python :: 3.9
Classifier: Programming Language :: Python :: 3.10
Classifier: Programming Language :: Python :: 3.11
Requires-Dist: pytest (>=7.1.3,<8.0.0)
